optimalagents/__init__.py
optimalagents/cli.py
optimalagents_power-0.2.0.dist-info/licenses/LICENSE
optimalagents_power-0.2.0.dist-info/METADATA
optimalagents_power-0.2.0.dist-info/WHEEL
optimalagents_power-0.2.0.dist-info/entry_points.txt
optimalagents_power-0.2.0.dist-info/top_level.txt
optimalagents_power-0.2.0.dist-info/RECORD
