Metadata-Version: 2.4
Name: OptimalAgents-power
Version: 0.2.0
Summary: A project generator for agents using FastAPI, Flask, or REST.
Home-page: https://github.com/sandilyaKishlay
Author: Sandilya Kishlay
Author-email: sandilyakishlay@gmail.com
Classifier: Programming Language :: Python :: 3
Classifier: License :: OSI Approved :: MIT License
Requires-Python: >=3.11
License-File: LICENSE
Requires-Dist: fastapi
Requires-Dist: flask
Requires-Dist: requests
Requires-Dist: uvicorn
Dynamic: author
Dynamic: author-email
Dynamic: classifier
Dynamic: description
Dynamic: description-content-type
Dynamic: home-page
Dynamic: license-file
Dynamic: requires-dist
Dynamic: requires-python
Dynamic: summary
